{
  "$schema": "https://typedoc.org/schema.json",
  "entryPoints": ["./src/index.ts"],
  "plugin": ["typedoc-plugin-coverage"],
  "exclude": ["**/node_modules/**", "**/temp/**", "**/test/**", "**/cst.d.ts"],
  "skipErrorChecking": true,
  "emit": "none",
  "requiredToBeDocumented": [
    "Accessor",
    "Class",
    "Enum",
    "EnumMember",
    "Function",
    "Interface",
    "Method",
    "Property",
    "TypeAlias",
    "Variable"
  ],
  "validation": {
    "notExported": false,
    "invalidLink": true,
    "notDocumented": true
  }
}
